{
    "error": false,
    "version": "twelve",
    "filename": "PixelOS_sweet-12.0-20220208-1809.zip",
    "datetime": "1644343662",
    "size": "1503613752",
    "url": "https://github.com/basamaryan/android_device_xiaomi_sweet/releases/download/test/PixelOS_sweet-12.0-20220208-1809.zip",
    "filehash": "e0632decd7c421216db2f7a00c10b172",
    "id": "e0632decd7c421216db2f7a00c10b172",
    "maintainers": [
        {
            "main_maintainer": true,
            "github_username": "https://github.com/basamaryan",
            "name": "Aryan"
        }
    ],
    "donate_url": "",
    "website_url": "https://github.com/PixelOS-Pixelish",
    "news_url": "https://t.me/PixelOSOfficial",
    "forum_url": ""
}
